ocench/__init__.py
ocench/aux_functions.py
ocench/calcular_NCH.py
ocench/example.py
ocench/ocench.py
ocench-0.0.7.dist-info/METADATA
ocench-0.0.7.dist-info/WHEEL
ocench-0.0.7.dist-info/licenses/LICENSE.txt
ocench-0.0.7.dist-info/RECORD
